<?xml version='1.0' encoding='utf-8'?>
<Resource><label commandName="UnableToDownloadFile" devLabel="Unknown error trying to download file" translation="尝试下载文件时出现未知错误" /><label commandName="BadStatusCode" devLabel="Bad http status code" translation="无效的 http 状态码" /><label commandName="UnableToIncrementalSearch" devLabel="Catch a unknown error when doing incremental search" translation="在执行增量搜索时发现未知错误" /><label commandName="PLM360_TradeMark" devLabel="PLM 360" translation="PLM 360" /><label commandName="UnableToAuthenticateWithToken" devLabel="Unknown exception error when authenticating with token" translation="使用令牌进行身份验证时出现未知异常错误" /><label commandName="PLM360CloseSaveDescription" devLabel="Save on Close." translation="关闭时保存。" /><label commandName="NotLoggedIn" devLabel="Must be logged in to perform this action." translation="必须登录才能执行此操作。" /><label commandName="PLM360OptionsName" devLabel="CAD 360 Options" translation="CAD 360 选项" /><label commandName="UnableToGetItemName" devLabel="Catch a unknown error when getting item name" translation="获取项目名称时发现未知错误" /><label commandName="PLM360MustBeAuthenticated" devLabel="Must be logged in!" translation="必须登录！" /><label commandName="PLM360AutoSaveDescription" devLabel="Auto save." translation="自动保存。" /><label commandName="PLM360OptionsDescription" devLabel="These are a set of options that are used for CAD 360 integration." translation="这是一组用于 CAD 360 集成的选项。" /><label commandName="RestServiceError" devLabel="Error calling REST endpoint" translation="调用 REST 端点时出错" /><label commandName="InvalidDocment" devLabel="Must supply a valid document." translation="必须提供有效的文档。" /></Resource>