<?xml version='1.0' encoding='utf-8'?>
<Resource><label commandName="e_MICRO" devLabel="micro" translation="micro" /><label commandName="UnitTypeFrequency" devLabel="Frequency" translation="周波数" /><label commandName="MinimumPrecisionValue3" devLabel="4.000" translation="4.000" /><label commandName="UnitScientificPrecisionToolTip" devLabel="How many decimal points should be displayed for the mantissa in scientific units" translation="科学的記数法単位の仮数部として表示する小数点以下の桁数を指定します" /><label commandName="e_SPEED_OF_LIGHT_CONSTANT" devLabel="SpeedOfLight" translation="SpeedOfLight" /><label commandName="GeneralUnitsValue4" devLabel="ft" translation="フィート" /><label commandName="GeneralUnitsValue2" devLabel="m" translation="m" /><label commandName="GeneralUnitsValue3" devLabel="in" translation="インチ" /><label commandName="GeneralUnitsValue0" devLabel="mm" translation="mm" /><label commandName="GeneralUnitsValue1" devLabel="cm" translation="cm" /><label commandName="UnitDisplaySymbolUserName" devLabel="Display symbols for units" translation="単位記号を表示" /><label commandName="MinimumPrecisionValue0" devLabel="4" translation="4" /><label commandName="UnitTypeEnergy" devLabel="Energy" translation="エネルギー" /><label commandName="UnitAngularPrecisionToolTip" devLabel="How many decimal points should be displayed for degree unit value" translation="度単位の値で表示する小数点以下の桁数です" /><label commandName="UnitGeneralUnitsUserName" devLabel="Default units for new documents" translation="新しいドキュメントの既定の単位" /><label commandName="e_HECTO" devLabel="hecto" translation="hecto" /><label commandName="modelingMassName" devLabel="Modeling Mass" translation="モデリングの質量" /><label commandName="GeneralPrecisionValue7" devLabel="0.1234567" translation="0.1234567" /><label commandName="UnitCompressUnitsUserName" devLabel="Compress Units" translation="圧縮単位" /><label commandName="e_KILO_ABBR" devLabel="k" translation="k" /><label commandName="NamedViewsSelectionId" devLabel="NamedViews" translation="名前付きビュー" /><label commandName="UnitTypeSpeed" devLabel="Speed" translation="速度" /><label commandName="GeneralPrecisionValue4" devLabel="0.1234" translation="0.1234" /><label commandName="ScientificPrecisionValue6" devLabel="1.123456E+04" translation="1.123456E + 04" /><label commandName="UnitTypeViscosity" devLabel="Viscosity" translation="粘度" /><label commandName="e_ACOS" devLabel="acos" translation="acos" /><label commandName="DecimalPointValueComma" devLabel="1,500" translation="1,500" /><label commandName="LengthDisplayValueFractional" devLabel="Fractional (e.g. 1 1/2\\" translation="分数表記(例: 1 1/2\\" /><label commandName="AreaProperty" devLabel="Area" translation="面積" /><label commandName="e_ATAN" devLabel="atan" translation="atan" /><label commandName="UnitTypeVolume" devLabel="Volume" translation="ボリューム" /><label commandName="e_SQRT" devLabel="sqrt" translation="sqrt" /><label commandName="UnitDegreeDisplayUserName" devLabel="Degree display format" translation="度の表示形式" /><label commandName="e_LN" devLabel="ln" translation="ln" /><label commandName="e_E_CONSTANT" devLabel="E" translation="E" /><label commandName="UnitTypeSubstance" devLabel="Substance" translation="物質" /><label commandName="UnitTypeCharge" devLabel="Charge" translation="電荷" /><label commandName="UnitDisplayScientificNotationBelowThresholdTip" devLabel="When the absolute value is less than this limit, display it in scientific notation" translation="絶対値がこの制限値より小さい場合、指数表記で表示します" /><label commandName="UnitTypeLuminousFlux" devLabel="LuminousFlux" translation="光束" /><label commandName="UnitDisplayMinimumPrecisionTip" devLabel="Minimum precison when hiding trailing zeroes, so 4.000 will display as 4.00 instead of 4" translation="末尾のゼロを非表示にすると精度が最小になるため、4.000 が 4 ではなく 4.00 と表示されます" /><label commandName="UnitDisplayMinimumPrecisionName" devLabel="Minimum precision when hiding trailing zeroes" translation="末尾のゼロを非表示にした場合の最小精度" /><label commandName="e_INCH" devLabel="inch" translation="inch" /><label commandName="UnitTypeMass" devLabel="Mass" translation="質量" /><label commandName="e_PICO" devLabel="pico" translation="pico" /><label commandName="VolumeProperty" devLabel="Volume" translation="ボリューム" /><label commandName="e_DECI_ABBR" devLabel="d" translation="d" /><label commandName="UnitTypeAngularVelocity" devLabel="AngularVelocity" translation="角速度" /><label commandName="UnitTypeMagnetizingField" devLabel="MagnetizingField" translation="磁場" /><label commandName="e_SIGN" devLabel="sign" translation="sign" /><label commandName="e_KILO" devLabel="kilo" translation="kilo" /><label commandName="e_EXP" devLabel="exp" translation="exp" /><label commandName="e_FOOT_ABBR" devLabel="ft" translation="フィート" /><label commandName="MinimumPrecisionValue8" devLabel="4.00000000" translation="4.00000000" /><label commandName="MinimumPrecisionValue7" devLabel="4.0000000" translation="4.0000000" /><label commandName="MinimumPrecisionValue6" devLabel="4.000000" translation="4.000000" /><label commandName="e_DOLLAR_SYM" devLabel="$" translation="$" /><label commandName="MinimumPrecisionValue4" devLabel="4.0000" translation="4.0000" /><label commandName="MaterialProperty" devLabel="Material" translation="マテリアル" /><label commandName="MinimumPrecisionValue2" devLabel="4.00" translation="4.00" /><label commandName="e_DECA_ABBR" devLabel="da" translation="da" /><label commandName="MassProperty" devLabel="Mass" translation="質量" /><label commandName="e_EXA" devLabel="exa" translation="exa" /><label commandName="UnitTypeAngle" devLabel="Angle" translation="角度" /><label commandName="AngularPrecisionValue0" devLabel="0" translation="0" /><label commandName="e_FLOOR" devLabel="floor" translation="floor" /><label commandName="UnitTypeTemperature" devLabel="Temperature" translation="温度" /><label commandName="e_ABS" devLabel="abs" translation="abs" /><label commandName="UnitTypePower" devLabel="Power" translation="電力" /><label commandName="VariedProperty" devLabel="(Various)" translation="(各種)" /><label commandName="UnitDisplayScientificNotationAboveThresholdName" devLabel="Use scientific notation above" translation="次の値より大きい場合に指数表記を使用:" /><label commandName="e_PETA" devLabel="peta" translation="peta" /><label commandName="e_DEGREE" devLabel="degree" translation="degree" /><label commandName="DensityProperty" devLabel="Density" translation="密度" /><label commandName="e_INCH_ABBR" devLabel="in" translation="インチ" /><label commandName="e_TERA_ABBR" devLabel="T" translation="T" /><label commandName="e_SINH" devLabel="sinh" translation="sinh" /><label commandName="ScientificAboveValue8" devLabel="99999999.9999" translation="99999999.9999" /><label commandName="ScientificAboveValue6" devLabel="999999.9999" translation="999999.9999" /><label commandName="ScientificAboveValue7" devLabel="9999999.9999" translation="9999999.9999" /><label commandName="ScientificAboveValue4" devLabel="9999.9999" translation="9999.9999" /><label commandName="ScientificAboveValue5" devLabel="99999.9999" translation="99999.9999" /><label commandName="ScientificAboveValue2" devLabel="99.9999" translation="99.9999" /><label commandName="ScientificAboveValue3" devLabel="999.9999" translation="999.9999" /><label commandName="ScientificAboveValue1" devLabel="9.9999" translation="9.9999" /><label commandName="LengthDisplayValueDecimal" devLabel="Decimal (e.g. 1.5 in)" translation="小数表記(例: 1.5 インチ)" /><label commandName="UnitScientificNotationToolTip" devLabel="Should a value be displayed using scientific notation if it is big or small (e.g. &gt; 1E3 or &lt; 1E-3)" translation="値が大きいまたは小さい場合(例: 1e3 超または 1e-3 未満)、値は指数表記で表示されます" /><label commandName="LengthDisplayValueArchitectural" devLabel="Architectural (e.g. 0\'-1 1/2\\" translation="建築図面表記(例: 0\'-1 1/2\\" /><label commandName="UnitTypeMagneticFlux" devLabel="MagneticFlux" translation="磁束" /><label commandName="UnitTypeForce" devLabel="Force" translation="力" /><label commandName="e_EXA_ABBR" devLabel="E" translation="E" /><label commandName="UnitGeneralPrecisionToolTip" devLabel="How many decimal points should be displayed for a general unit value" translation="一般的な単位値で表示する小数点以下の桁数を設定します" /><label commandName="UnitLengthDisplayToolTip" devLabel="How to display length in feet and inches - decimal (1.5 inches), fractional (1 1/2\\" translation="フィート単位とインチ単位での長さの表示方法 - 小数(1.5 インチ)、分数(1 1/2 " /><label commandName="UnitDecimalPointIsFullStopUserName" devLabel="Decimal point display" translation="小数点表示" /><label commandName="ScientificPrecisionValue9" devLabel="1.123456789E+04" translation="1.123456789E + 04" /><label commandName="ScientificPrecisionValue8" devLabel="1.12345678E+04" translation="1.12345678E + 04" /><label commandName="UnitLengthDisplayUserName" devLabel="Foot and inch foot display format" translation="フィートとインチの表示形式" /><label commandName="e_DEGREE_SYM" devLabel="\xb0" translation="\xb0" /><label commandName="ScientificPrecisionValue4" devLabel="1.1234E+04" translation="1.1234E + 04" /><label commandName="ScientificPrecisionValue7" devLabel="1.1234567E+04" translation="1.1234567E + 04" /><label commandName="e_SIN" devLabel="sin" translation="sin" /><label commandName="ScientificPrecisionValue1" devLabel="1.1E+04" translation="1.1E + 04" /><label commandName="ScientificPrecisionValue0" devLabel="1E+04" translation="1E + 04" /><label commandName="ScientificPrecisionValue3" devLabel="1.123E+04" translation="1.123E + 04" /><label commandName="ScientificPrecisionValue2" devLabel="1.12E+04" translation="1.12E + 04" /><label commandName="UnitCompressUnitsToolTip" devLabel="Should units be compressed using powers (e.g. m^3) or simply multiplied (e.g. m m m)" translation="単位は累乗(例: m^3)または単純な乗算(例: m m m)を使用して圧縮表示されます" /><label commandName="e_MILLI_ABBR" devLabel="m" translation="m" /><label commandName="ScientificBelowValue2" devLabel="0.01" translation="0.01" /><label commandName="UnitDisplayScientificNotationAboveThresholdTip" devLabel="When the absolute value of a number is greater than this limit, display it in scientific notation" translation="数値の絶対値がこの制限を超える場合に指数表記で表示します" /><label commandName="e_GRAVITY_CONSTANT" devLabel="Gravity" translation="Gravity" /><label commandName="e_CENTI" devLabel="centi" translation="centi" /><label commandName="e_ATTO_ABBR" devLabel="a" translation="a" /><label commandName="UnitTypeCurrency" devLabel="Currency" translation="通貨" /><label commandName="DecimalPointValueFullStop" devLabel="1.500" translation="1.500" /><label commandName="e_GIGA" devLabel="giga" translation="giga" /><label commandName="UnitDecimalPointIsFullStopToolTip" devLabel="Should a decimal point be displayed as a full stop or a comma" translation="小数点をピリオドまたはカンマで表示します" /><label commandName="e_ASIN" devLabel="asin" translation="asin" /><label commandName="e_COS" devLabel="cos" translation="cos" /><label commandName="e_DECI" devLabel="deci" translation="deci" /><label commandName="UnitDisplayScientificNotationBelowThresholdName" devLabel="Use scientific notation below" translation="次の値未満の場合に指数表記を使用:" /><label commandName="e_CEIL" devLabel="ceil" translation="ceil" /><label commandName="e_DECA" devLabel="deca" translation="deca" /><label commandName="UnitTypeTime" devLabel="Time" translation="時間" /><label commandName="e_NANO_ABBR" devLabel="n" translation="n" /><label commandName="UnitDegreeDisplayToolTip" devLabel="How should fractions of a degree be displayed - decimal (39.25 deg) or deg / min / sec (39 deg 15\')" translation="度数の分数の表示方法 - 小数(39.25 度)または度/分/秒(39 度 15\')" /><label commandName="UnitTypeLuminosity" devLabel="Luminosity" translation="明度" /><label commandName="NamedViewSelectionId" devLabel="NamedView" translation="名前付きビュー" /><label commandName="GeneralPrecisionValue9" devLabel="0.123456789" translation="0.123456789" /><label commandName="e_CENTI_ABBR" devLabel="c" translation="c" /><label commandName="e_NANO" devLabel="nano" translation="nano" /><label commandName="UnitTypeResistance" devLabel="Resistance" translation="抵抗" /><label commandName="GeneralPrecisionValue3" devLabel="0.123" translation="0.123" /><label commandName="GeneralPrecisionValue2" devLabel="0.12" translation="0.12" /><label commandName="GeneralPrecisionValue1" devLabel="0.1" translation="0.1" /><label commandName="GeneralPrecisionValue0" devLabel="0" translation="0" /><label commandName="e_FEMTO" devLabel="femto" translation="femto" /><label commandName="GeneralPrecisionValue6" devLabel="0.123456" translation="0.123456" /><label commandName="GeneralPrecisionValue5" devLabel="0.12345" translation="0.12345" /><label commandName="MinimumPrecisionValue1" devLabel="4.0" translation="4.0" /><label commandName="DegreeDisplayValueDecimal" devLabel="Decimal (e.g. 39.25 deg)" translation="十進表記(例: 39.25 度)" /><label commandName="UnitGeneralPrecisionUserName" devLabel="General precision" translation="一般的な精度" /><label commandName="e_MIN" devLabel="min" translation="min" /><label commandName="UnitDisplaySymbolToolTip" devLabel="Should units be displayed with their symbol (if they have one) rather than their abbreviation or full name" translation="単位は略号または完全表記ではなく、記号(ある場合)で表示されます" /><label commandName="e_ATTO" devLabel="atto" translation="atto" /><label commandName="UnitDisplayAbbreviatedUserName" devLabel="Display abbreviations for units" translation="単位の略号を表示" /><label commandName="UnitDisplayAbbreviatedToolTip" devLabel="Should units be displayed with their abbreviation (if they have one) instead of their full name" translation="単位は完全表記ではなく略号(ある場合)で表示されます" /><label commandName="e_TANH" devLabel="tanh" translation="tanh" /><label commandName="UnitTypeSolidAngle" devLabel="SolidAngle" translation="立体角" /><label commandName="UnitDisplayHideTrailingZeroesTip" devLabel="Should trailing zeroes be hidden - e.g. display 4.020 as 4.02" translation="末尾ゼロを非表示にします - 例: 4.020 を 4.02 と表示" /><label commandName="UnitDisplaySettingsOptionsUserName" devLabel="Units" translation="単位" /><label commandName="e_POW" devLabel="pow" translation="pow" /><label commandName="e_MICRO_ABBR" devLabel="micro" translation="micro" /><label commandName="e_FEMTO_ABBR" devLabel="f" translation="f" /><label commandName="ScientificBelowValue6" devLabel="0.000001" translation="0.000001" /><label commandName="ScientificBelowValue7" devLabel="0.0000001" translation="0.0000001" /><label commandName="ScientificBelowValue4" devLabel="0.0001" translation="0.0001" /><label commandName="ScientificBelowValue5" devLabel="0.00001" translation="0.00001" /><label commandName="e_PICO_ABBR" devLabel="p" translation="p" /><label commandName="ScientificBelowValue3" devLabel="0.001" translation="0.001" /><label commandName="ScientificBelowValue1" devLabel="0.1" translation="0.1" /><label commandName="e_PETA_ABBR" devLabel="P" translation="P" /><label commandName="e_MEGA_ABBR" devLabel="M" translation="M" /><label commandName="ScientificBelowValue8" devLabel="0.00000001" translation="0.00000001" /><label commandName="e_DEGREE_ABBR" devLabel="deg" translation="deg" /><label commandName="e_GIGA_ABBR" devLabel="G" translation="G" /><label commandName="e_LOG" devLabel="log" translation="log" /><label commandName="UnitTypeConductance" devLabel="Conductance" translation="伝導率" /><label commandName="e_RANDOM" devLabel="random" translation="random" /><label commandName="UnitsAndValueGroupUserName" devLabel="Unit &amp; Value Display" translation="単位と値の表示" /><label commandName="e_TERA" devLabel="tera" translation="tera" /><label commandName="e_COSH" devLabel="cosh" translation="cosh" /><label commandName="e_MAX" devLabel="max" translation="max" /><label commandName="UnitTypeLength" devLabel="Length" translation="長さ" /><label commandName="UnitTypeCapacitance" devLabel="Capacitance" translation="静電容量" /><label commandName="e_TAN" devLabel="tan" translation="tan" /><label commandName="UnitTypeInductance" devLabel="Inductance" translation="インダクタンス" /><label commandName="UnitDisplaySettingsOptionsToolTip" devLabel="Preferences that control how units and values are displayed" translation="単位および値の表示方法をコントロールする環境設定" /><label commandName="UnitTypeCurrent" devLabel="Current" translation=" 電流" /><label commandName="DegreeDisplayValueDegMinSec" devLabel="Minutes and Seconds (e.g. 39 deg 15\\\')" translation="分と秒(例: 39 度 15\\\')" /><label commandName="e_PI_CONSTANT" devLabel="PI" translation="PI" /><label commandName="DefaultUnitsGroupToolTip" devLabel="" translation="" /><label commandName="UnitTypePressure" devLabel="Pressure" translation="圧力" /><label commandName="DefaultUnitsGroupUserName" devLabel="Fusion Default Units" translation="Fusion の既定の単位" /><label commandName="ScientificPrecisionValue5" devLabel="1.12345E+04" translation="1.12345E + 04" /><label commandName="UnitTypeElectromotiveForce" devLabel="ElectromotiveForce" translation="起電力" /><label commandName="UnitScientificNotationUserName" devLabel="Use scientific notation for big and small values" translation="大きい値と小さい値に指数表記を使用" /><label commandName="AngularPrecisionValue4" devLabel="0.1234" translation="0.1234" /><label commandName="UnitDisplayHideTrailingZeroesName" devLabel="Hide trailing zeroes" translation="末尾のゼロを非表示" /><label commandName="UnitTypeIlluminance" devLabel="Illuminance" translation="照度" /><label commandName="UnitScientificPrecisionUserName" devLabel="Scientific notation precision" translation="指数表記の精度" /><label commandName="e_HECTO_ABBR" devLabel="h" translation="h" /><label commandName="e_MILLI" devLabel="milli" translation="milli" /><label commandName="UnitTypeArea" devLabel="Area" translation="面積" /><label commandName="UnitsAndValueGroupToolTip" devLabel="" translation="" /><label commandName="e_FOOT" devLabel="foot" translation="foot" /><label commandName="UnitGeneralUnitsToolTip" devLabel="Default unit system for new documents" translation="新しいドキュメントの既定の単位系" /><label commandName="UnitAngularPrecisionUserName" devLabel="Angular precision" translation="角度寸法の精度" /><label commandName="modelingLengthName" devLabel="Modeling Length" translation="モデリングの長さ" /><label commandName="e_ROUND" devLabel="round" translation="round" /><label commandName="GeneralPrecisionValue8" devLabel="0.12345678" translation="0.12345678" /><label commandName="AngularPrecisionValue9" devLabel="0.123456789" translation="0.123456789" /><label commandName="AngularPrecisionValue8" devLabel="0.12345678" translation="0.12345678" /><label commandName="UnitTypeMagneticField" devLabel="MagneticField" translation="磁場" /><label commandName="AngularPrecisionValue5" devLabel="0.12345" translation="0.12345" /><label commandName="e_MEGA" devLabel="mega" translation="mega" /><label commandName="AngularPrecisionValue7" devLabel="0.1234567" translation="0.1234567" /><label commandName="AngularPrecisionValue6" devLabel="0.123456" translation="0.123456" /><label commandName="AngularPrecisionValue1" devLabel="0.1" translation="0.1" /><label commandName="MinimumPrecisionValue5" devLabel="4.00000" translation="4.00000" /><label commandName="AngularPrecisionValue3" devLabel="0.123" translation="0.123" /><label commandName="AngularPrecisionValue2" devLabel="0.12" translation="0.12" /></Resource>