<?xml version="1.0" encoding="utf-8"?>
<Configurations>
    <WebServices>
        <Urls>
            <RequestTokenEndPoint>/OAuth/RequestToken</RequestTokenEndPoint>
            <AccessTokenEndPoint>/OAuth/AccessToken</AccessTokenEndPoint>
            <AuthorizationEndPoint>/OAuth/Authorize?viewmode=desktop&amp;oauth_token=</AuthorizationEndPoint>
            <InvalidateTokenEndPoint>/OAuth/InvalidateToken</InvalidateTokenEndPoint>
            <AccountServerUrl>https://accounts-staging.autodesk.com</AccountServerUrl>
            <LoggedInServerMenuEndPoint>/api/settings/v1/user/@me</LoggedInServerMenuEndPoint>
            <LoggedOutServerMenuEndPoint>/api/settings/v1/user</LoggedOutServerMenuEndPoint>
            <IdentityAccountFolderEndPoint>/api/accounts/v1/user/@me</IdentityAccountFolderEndPoint>
            <LoggedInUrlEndPoint>/OAuth/Allow</LoggedInUrlEndPoint>
            <RegisterEndPoint>/register</RegisterEndPoint>
            <UpdateProfileEndPoint>/users/%1/view?viewmode=desktop</UpdateProfileEndPoint>
            <LearnMorePageUrl>http://www.autodesk.com</LearnMorePageUrl>
            <StorageOnlineUrl>https://360-staging.autodesk.com/</StorageOnlineUrl>
            <StorageApiUrl>https://api-staging.autodesk.com</StorageApiUrl>
            <StorageRoot>dav</StorageRoot>
            <StorageUsageEndPoint>/storage/usage/v1/user/@me/service/my</StorageUsageEndPoint>
            <ShareUrl>https://360-staging.autodesk.com/Sharing/Status</ShareUrl>
            <ShareStatusUrl>https://360-staging.autodesk.com/api/v1/Sharing/Status</ShareStatusUrl>
            <NitrogenStorageEndPoint>storage/dav/service/@default/user/@me</NitrogenStorageEndPoint>
            <NitrogenStorageEndPointRestFolder>storage/folders/v1/user/@me/service/@default/folder</NitrogenStorageEndPointRestFolder>
            <NitrogenStorageEndPointRestFile>storage/files/v1/user/@me/service/@default/folder/@any/file</NitrogenStorageEndPointRestFile>
            <NitrousStorageEndPoint>storage/dav/service/my/user/@me</NitrousStorageEndPoint>
            <NitrousStorageEndPointRestFolder>storage/folders/v1/user/@me/service/my/folder</NitrousStorageEndPointRestFolder>
            <NitrousStorageEndPointRestFile>storage/files/v1/user/@me/service/my/folder/@any/file</NitrousStorageEndPointRestFile>
            <OAuthRedirect>/oAuth/OAuthRedirect</OAuthRedirect>
            <ExchangeUrl>http://exchange-staging.autodesk.com/apps/v1</ExchangeUrl>
            <ExchangeUrlParameters>utm_source=inproduct&amp;utm_medium=infocenter</ExchangeUrlParameters>
            <SyncInstallFailedHelpUrl>http://www.autodesk.com/adsync-installer</SyncInstallFailedHelpUrl>
            <SyncUpdateUrl>http://com.autodesk.storage.public.staging.s3.amazonaws.com/sync/liveupdate/updates.xml</SyncUpdateUrl>
            <StorageOptionsUrl>https://accounts.autodesk.com?section=cloud</StorageOptionsUrl>
            <TroubleshootSyncErrorsUrl>http://www.autodesk.com/adsync-error</TroubleshootSyncErrorsUrl>
            <PatchFileRestEndPoint>storage/files/v1/user/@me/service/my/folder/@any/file/%FileId%/versions/%VersionId%</PatchFileRestEndPoint>
            <SyncConfigUrl>http://com.autodesk.storage.public.staging.s3.amazonaws.com/sync/config.xml</SyncConfigUrl>
            <ReferenceConfigUrl>https://references-staging.api.autodesk.com/reference/v1/configInfo</ReferenceConfigUrl>
            <ReferenceUrl>https://references-staging.api.autodesk.com</ReferenceUrl>
            <ReferenceEndPointPostRefs>reference/v1/refs</ReferenceEndPointPostRefs>
            <ReferenceEndPointGetRefs>reference/v1/asset/%AssetLocators%/children/dependency</ReferenceEndPointGetRefs>
            <NitrogenFileUrnNamespace>urn:adsk.nitrogen:fs.file</NitrogenFileUrnNamespace>
            <ShareFileInBrowserEndPoint>api/Item/FileDetails</ShareFileInBrowserEndPoint>
            <ShareFolderInBrowserEndPoint>api/Item/FolderDetails</ShareFolderInBrowserEndPoint>
            <HelpUrl>http://www.autodesk.com/adsk360-help-faq</HelpUrl>
            <ChangeServiceUrl>https://changes-staging.api.autodesk.com</ChangeServiceUrl>
            <InitiateBaseLineNitrousEndPoint>baseline/v1/user/@me/service/my</InitiateBaseLineNitrousEndPoint>
            <InitiateBaseLineNitrogenEndPoint>baseline/v1/user/@me/service/@default</InitiateBaseLineNitrogenEndPoint>
        </Urls>
    </WebServices>
</Configurations>
